vsdkx_core-1.0-py3.10-nspkg.pth
vsdkx/core/__init__.py
vsdkx/core/detector.py
vsdkx/core/interfaces.py
vsdkx/core/runner.py
vsdkx/core/structs.py
vsdkx/core/util/__init__.py
vsdkx/core/util/drawing.py
vsdkx/core/util/imp.py
vsdkx/core/util/io.py
vsdkx/core/util/model.py
vsdkx_core-1.0.dist-info/LICENSE
vsdkx_core-1.0.dist-info/METADATA
vsdkx_core-1.0.dist-info/WHEEL
vsdkx_core-1.0.dist-info/namespace_packages.txt
vsdkx_core-1.0.dist-info/top_level.txt
vsdkx_core-1.0.dist-info/RECORD
