Metadata-Version: 2.1
Name: vsdkx-core
Version: 1.0
Summary: UNKNOWN
Home-page: https://github.com/natix-io/vsdkx-core
Author: Helmut
Author-email: helmut@natix.io
License: UNKNOWN
Platform: UNKNOWN
License-File: LICENSE
Requires-Dist: vsdkx-connector
Requires-Dist: argparse
Requires-Dist: opencv-python (~=4.2.0.34)
Requires-Dist: pyyaml
Requires-Dist: numpy (>=1.18.5)
Requires-Dist: tensorflow
